geomet/__init__.py
geomet/esri.py
geomet/geopackage.py
geomet/tool.py
geomet/util.py
geomet/wkb.py
geomet/wkt.py
geomet-1.0.0.dist-info/AUTHORS.txt
geomet-1.0.0.dist-info/LICENSE
geomet-1.0.0.dist-info/METADATA
geomet-1.0.0.dist-info/WHEEL
geomet-1.0.0.dist-info/entry_points.txt
geomet-1.0.0.dist-info/top_level.txt
geomet-1.0.0.dist-info/RECORD
